README.md
setup.py
spellcheck/__init__.py
spellcheck/spellcheck.py
spellcheck.egg-info/PKG-INFO
spellcheck.egg-info/SOURCES.txt
spellcheck.egg-info/dependency_links.txt
spellcheck.egg-info/top_level.txt