Metadata-Version: 2.1
Name: spellcheck
Version: 1.0.2
Summary: Simple spellcheck tool
Home-page: https://github.com/LilChickenz/spellcheck
Author: Polloz
License: UNKNOWN
Platform: UNKNOWN
Classifier: Programming Language :: Python :: 3
Classifier: License :: OSI Approved :: MIT License
Classifier: Operating System :: OS Independent
